container_app_conf/__init__.py
container_app_conf/const.py
container_app_conf/util.py
container_app_conf/entry/__init__.py
container_app_conf/entry/bool.py
container_app_conf/entry/date.py
container_app_conf/entry/dict.py
container_app_conf/entry/file.py
container_app_conf/entry/float.py
container_app_conf/entry/int.py
container_app_conf/entry/list.py
container_app_conf/entry/range.py
container_app_conf/entry/regex.py
container_app_conf/entry/string.py
container_app_conf/entry/timedelta.py
container_app_conf/formatter/__init__.py
container_app_conf/formatter/json.py
container_app_conf/formatter/toml.py
container_app_conf/formatter/yaml.py
container_app_conf/source/__init__.py
container_app_conf/source/env_source.py
container_app_conf/source/json_source.py
container_app_conf/source/toml_source.py
container_app_conf/source/yaml_source.py
tests/__init__.py
tests/config_keys_test.py
tests/entry_test.py
tests/generate_reference_config_test.py
tests/list_entry_test.py
tests/print_test.py
tests/secret_test.py
tests/singleton_test.py
tests/data_source/__init__.py
tests/data_source/ignore_case_test.py
tests/data_source/source_test.py
container_app_conf-5.3.0.dist-info/LICENSE
container_app_conf-5.3.0.dist-info/METADATA
container_app_conf-5.3.0.dist-info/WHEEL
container_app_conf-5.3.0.dist-info/top_level.txt
container_app_conf-5.3.0.dist-info/RECORD
