Metadata-Version: 2.1
Name: container_app_conf
Version: 5.3.0
Summary: Convenient configuration of containerized applications
Home-page: https://github.com/markusressel/container-app-conf
Author: Markus Ressel
Author-email: mail@markusressel.de
License: MIT
Classifier: Development Status :: 5 - Production/Stable
Classifier: License :: OSI Approved :: MIT License
Classifier: Programming Language :: Python :: 3
Classifier: Programming Language :: Python :: 3.8
Classifier: Programming Language :: Python :: 3.9
Classifier: Programming Language :: Python :: 3.10
Classifier: Programming Language :: Python :: 3.11
License-File: LICENSE
Requires-Dist: py-range-parse
Requires-Dist: python-dateutil
Requires-Dist: pytimeparse
Requires-Dist: ruamel.yaml
Requires-Dist: ruamel.yaml.clib
Requires-Dist: six
Requires-Dist: toml
Requires-Dist: voluptuous
